Metadata-Version: 2.1
Name: gapp
Version: 1.0.2
Summary: easy buttons and other graphics elements to control the code.
Home-page: https://github.com/Madoshakalaka/gapp
Author: Matt Yan
Author-email: syan4@ualberta.ca
License: UNKNOWN
Project-URL: Bug Reports, https://github.com/Madoshakalaka/gapp/issues
Project-URL: Funding, https://github.com/Madoshakalaka/gapp
Project-URL: Say Thanks!, https://github.com/Madoshakalaka/gapp
Project-URL: Source, https://github.com/Madoshakalaka/gapp
Platform: UNKNOWN
Classifier: Development Status :: 3 - Alpha
Classifier: Intended Audience :: Developers
Classifier: Topic :: Software Development :: Build Tools
Classifier: License :: OSI Approved :: MIT License
Classifier: Programming Language :: Python :: 3.6
Classifier: Programming Language :: Python :: 3.7
Requires-Python: >=3.6
